numbers_complex/__init__.py
numbers_complex-0.0.1.dist-info/LICENSE.txt
numbers_complex-0.0.1.dist-info/METADATA
numbers_complex-0.0.1.dist-info/WHEEL
numbers_complex-0.0.1.dist-info/top_level.txt
numbers_complex-0.0.1.dist-info/RECORD
